dtrack-0.0.1.dist-info/METADATA
dtrack-0.0.1.dist-info/WHEEL
dtrack.py
dtrack-0.0.1.dist-info/RECORD
