Metadata-Version: 2.1
Name: dtrack
Version: 0.0.1
Summary: CLI for Dependency-Track
License: MIT
Requires-Python: >=3.11
